MANIFEST.in
README.md
setup.py
SignFinder/__init__.py
SignFinder/__main__.py
SignFinder.egg-info/PKG-INFO
SignFinder.egg-info/SOURCES.txt
SignFinder.egg-info/dependency_links.txt
SignFinder.egg-info/entry_points.txt
SignFinder.egg-info/not-zip-safe
SignFinder.egg-info/requires.txt
SignFinder.egg-info/top_level.txt
SignFinder/core/__init__.py
SignFinder/core/config.py
SignFinder/core/core.py
SignFinder/core/data_buffer.py
SignFinder/core/file_manager.py
SignFinder/core/input_parser.py
SignFinder/core/plugin_aux.py
SignFinder/core/plugin_manager.py
SignFinder/core/preload_cmd.py
SignFinder/core/riposte_sf/README.md
SignFinder/core/riposte_sf/__init__.py
SignFinder/core/riposte_sf/command.py
SignFinder/core/riposte_sf/completer.py
SignFinder/core/riposte_sf/data_vars.py
SignFinder/core/riposte_sf/exceptions.py
SignFinder/core/riposte_sf/flag_parser.py
SignFinder/core/riposte_sf/guides.py
SignFinder/core/riposte_sf/input_streams.py
SignFinder/core/riposte_sf/printer.py
SignFinder/core/riposte_sf/riposte.py
SignFinder/core/utils/ByteTools.py
SignFinder/core/utils/EncTools.py
SignFinder/core/utils/FileTools.py
SignFinder/core/utils/RangeTools.py
SignFinder/core/utils/TextParser.py
SignFinder/core/utils/__init__.py
SignFinder/plugins/__init__.py
SignFinder/plugins/command_div.py
SignFinder/plugins/command_elf_info.py
SignFinder/plugins/command_fill.py
SignFinder/plugins/command_half.py
SignFinder/plugins/command_pe_info.py
SignFinder/plugins/command_vd.py
SignFinder/plugins/module_capstone.py
SignFinder/plugins/module_elf.py
SignFinder/plugins/module_pe32.py